<?xml version="1.0" encoding="utf-8" ?><dwsync><file name="beige.scss" server="www.nestorcbello.com" local="3481330076" remote="12084357752" Dst="-1" /><file name="blood.scss" server="www.nestorcbello.com" local="3481330076" remote="12084357752" Dst="-1" /><file name="default.scss" server="www.nestorcbello.com" local="3481330076" remote="12084357752" Dst="-1" /><file name="moon.scss" server="www.nestorcbello.com" local="3481330076" remote="12084357752" Dst="-1" /><file name="night.scss" server="www.nestorcbello.com" local="3481330076" remote="12084357752" Dst="-1" /><file name="serif.scss" server="www.nestorcbello.com" local="3481330076" remote="12084357752" Dst="-1" /><file name="simple.scss" server="www.nestorcbello.com" local="3481330076" remote="12084357752" Dst="-1" /><file name="sky.scss" server="www.nestorcbello.com" local="3481330076" remote="12084357752" Dst="-1" /><file name="solarized.scss" server="www.nestorcbello.com" local="3481330076" remote="12084357752" Dst="-1" /></dwsync>